magicpyden/__init__.py
magicpyden/api.py
magicpyden/constants.py
magicpyden/endpoint.py
magicpyden/schema.py
magicpyden/types.py
magicpyden-0.1.4.dist-info/LICENSE
magicpyden-0.1.4.dist-info/WHEEL
magicpyden-0.1.4.dist-info/METADATA
magicpyden-0.1.4.dist-info/RECORD
