Metadata-Version: 2.1
Name: magicpyden
Version: 0.1.4
Summary: Async Python API wrapper for MagicEden
Keywords: async,api,magic eden
Author: Christian Pérez Villanueva
Author-email: perez.villanueva.christian34@gmail.com
Requires-Python: >=3.8,<4.0
Classifier: Programming Language :: Python :: 3
Classifier: Programming Language :: Python :: 3.10
Classifier: Programming Language :: Python :: 3.8
Classifier: Programming Language :: Python :: 3.9
Requires-Dist: aiohttp[speedups] (>=3.8.1,<4.0.0)
Requires-Dist: inflection (>=0.5.1,<0.6.0)
Requires-Dist: pydantic (>=1.9.0,<2.0.0)
